updatehub/__init__.py
updatehub/api.py
updatehub/listener.py
updatehub_agent_sdk-2.0.0.dist-info/LICENSE
updatehub_agent_sdk-2.0.0.dist-info/METADATA
updatehub_agent_sdk-2.0.0.dist-info/WHEEL
updatehub_agent_sdk-2.0.0.dist-info/top_level.txt
updatehub_agent_sdk-2.0.0.dist-info/RECORD
