Metadata-Version: 2.1
Name: updatehub-agent-sdk
Version: 2.0.0
Summary: UpdateHub's agent SDK for Python
Home-page: http://www.ossystems.com.br
Author: O.S. Systems Software LTDA
Author-email: contato@ossystems.com.br
License: MIT
Keywords: industrial-linux embedded-linux embedded firmware-updates linux update-service
Platform: UNKNOWN
Classifier: License :: OSI Approved :: MIT License
Requires-Python: >=3.5, <4
